po_publish/__init__.py
po_publish/license.txt
po_publish/script.py
po_publish/top_level.txt
po_publish-0.1.0.dist-info/entry_points.txt
po_publish-0.1.0.dist-info/WHEEL
po_publish-0.1.0.dist-info/METADATA
po_publish-0.1.0.dist-info/RECORD
